{ "type": "class",
  "qname": "org.apache.royale.svg.Path",
  "baseClassname": "org.apache.royale.svg.GraphicShape"
  ,
  "members": [
  { "type": "accessor",
        "access": "read-write",
        "return": "String",
        "qname": "data",
        "namespace": "public",
        "bindable": [],
        "details": [],
        "deprecated": {}},
      { "type": "accessor",
        "access": "read-write",
        "return": "org.apache.royale.graphics.PathBuilder",
        "qname": "pathCommands",
        "namespace": "public",
        "bindable": [],
        "details": [],
        "deprecated": {}},
      { "type": "method",
        "qname": "drawPathCommands",
        "namespace": "public",
        "bindable": [],
        "details": [],
        "deprecated": {},
          "description": "Draw the path.",
        "tags": [
        {  "tagName": "param",
               "values": ["data A PathBuilder object containing a vector of drawing commands."]},
            {  "tagName": "playerversion",
               "values": ["Flash 10.2", "AIR 2.6"]},
            {  "tagName": "productversion",
               "values": ["Royale 0.0"]},
            {  "tagName": "royaleignorecoercion",
               "values": ["org.apache.royale.core.WrappedHTMLElement"]},
            {  "tagName": "langversion",
               "values": ["3.0"]}  ],
          "return": "void",
          "params": [{ "name": "xp", "type": "Number"},
        { "name": "yp", "type": "Number"},
        { "name": "data", "type": "org.apache.royale.graphics.PathBuilder"}]}
      ,
      { "type": "method",
        "qname": "drawStringPath",
        "namespace": "public",
        "bindable": [],
        "details": [],
        "deprecated": {},
          "description": "Draw the path. The value is a space-delimited string describing each path segment. Each segment entry has a single character which denotes the segment type and two or more segment parameters.  If the segment command is upper-case, the parameters are absolute values. If the segment command is lower-case, the parameters are relative values.",
        "tags": [
        {  "tagName": "param",
               "values": ["data A string containing a compact represention of the path segments."]},
            {  "tagName": "playerversion",
               "values": ["Flash 10.2", "AIR 2.6"]},
            {  "tagName": "productversion",
               "values": ["Royale 0.0"]},
            {  "tagName": "royaleignorecoercion",
               "values": ["org.apache.royale.core.WrappedHTMLElement"]},
            {  "tagName": "langversion",
               "values": ["3.0"]}  ],
          "return": "void",
          "params": [{ "name": "xp", "type": "Number"},
        { "name": "yp", "type": "Number"},
        { "name": "data", "type": "String"}]}
      ,
      { "type": "method",
        "qname": "drawImpl",
        "namespace": "protected",
        "bindable": [],
        "details": ["override"],
        "deprecated": {},
          "return": "void",
          "params": []}
      ,
      { "type": "method",
        "qname": "draw",
        "namespace": "public",
        "bindable": [],
        "details": [],
        "deprecated": {},
          "return": "void",
          "params": []}
      ]
  }
