{ "type": "class",
  "qname": "org.apache.royale.jewel.beads.views.DataGridView",
  "baseClassname": "org.apache.royale.html.beads.GroupView"
  ,
    "description": "The DataGridView class is the visual bead for the org.apache.royale.jewel.DataGrid. This class constructs the items that make the DataGrid: Lists for each column and a org.apache.royale.jewel.ButtonBar for the column headers.  Columns without specific columnWidths gets 1/n of the maximun space available where n is the number of columns.",
  "tags": [
  {  "tagName": "viewbead",
         "values": []},
      {  "tagName": "playerversion",
         "values": ["Flash 10.2", "AIR 2.6"]},
      {  "tagName": "productversion",
         "values": ["Royale 0.9.7"]},
      {  "tagName": "langversion",
         "values": ["3.0"]}  ],
  "members": [
  { "type": "method",
        "qname": "org.apache.royale.jewel.beads.views.DataGridView",
        "namespace": "",
        "bindable": [],
        "details": [],
        "deprecated": {},
          "description": "constructor.",
        "tags": [
        {  "tagName": "playerversion",
               "values": ["Flash 10.2", "AIR 2.6"]},
            {  "tagName": "productversion",
               "values": ["Royale 0.9.7"]},
            {  "tagName": "langversion",
               "values": ["3.0"]}  ],
          "return": "",
          "params": []}
      ,
      { "type": "field",
        "qname": "_dg",
        "return": "org.apache.royale.core.IDataGrid",
        "namespace": "protected",
        "bindable": [],
        "details": [],
        "deprecated": {},
          "description": "",
        "tags": [
          ]},
      { "type": "field",
        "qname": "sharedModel",
        "return": "org.apache.royale.core.IDataGridModel",
        "namespace": "protected",
        "bindable": [],
        "details": [],
        "deprecated": {},
          "description": "",
        "tags": [
          ]},
      { "type": "accessor",
        "access": "write-only",
        "return": "org.apache.royale.core.IStrand",
        "qname": "strand",
        "namespace": "public",
        "bindable": [],
        "details": ["override"],
        "deprecated": {},
          "description": "",
        "tags": [
          ]},
      { "type": "method",
        "qname": "scrollToIndex",
        "namespace": "public",
        "bindable": [],
        "details": [],
        "deprecated": {},
          "description": "Ensures that the data provider item at the given index is visible.  If the item is visible, the <code>verticalScrollPosition</code> property is left unchanged even if the item is not the first visible item. If the item is not currently visible, the <code>verticalScrollPosition</code> property is changed make the item the first visible item, unless there aren't enough rows to do so because the <code>verticalScrollPosition</code> value is limited by the <code>maxVerticalScrollPosition</code> property.",
        "tags": [
        {  "tagName": "param",
               "values": ["index The index of the item in the data provider."]},
            {  "tagName": "playerversion",
               "values": ["Flash 9", "AIR 1.1"]},
            {  "tagName": "productversion",
               "values": ["Royale 0.9.10"]},
            {  "tagName": "return",
               "values": ["<code>true</code> if <code>verticalScrollPosition</code> changed."]},
            {  "tagName": "langversion",
               "values": ["3.0"]}  ],
          "return": "Boolean",
          "params": [{ "name": "index", "type": "int"}]}
      ,
      { "type": "method",
        "qname": "setColumnHeight",
        "namespace": "protected",
        "bindable": [],
        "details": [],
        "deprecated": {},
          "description": "set the height of the column if necessary",
        "tags": [
          ],
          "return": "void",
          "params": [{ "name": "column", "type": "org.apache.royale.core.StyledUIBase"}]}
      ,
      { "type": "method",
        "qname": "destroyLists",
        "namespace": "protected",
        "bindable": [],
        "details": [],
        "deprecated": {},
          "description": "",
        "tags": [
          ],
          "return": "void",
          "params": []}
      ,
      { "type": "method",
        "qname": "createColumnList",
        "namespace": "protected",
        "bindable": [],
        "details": [],
        "deprecated": {},
          "description": "",
        "tags": [
          ],
          "return": "org.apache.royale.jewel.supportClasses.datagrid.IDataGridColumnList",
          "params": [{ "name": "index", "type": "int"},
        { "name": "len", "type": "int"},
        { "name": "dataGridColumn", "type": "org.apache.royale.jewel.supportClasses.datagrid.IDataGridColumn"}]}
      ,
      { "type": "method",
        "qname": "initCompleteHandler",
        "namespace": "protected",
        "bindable": [],
        "details": [],
        "deprecated": {},
          "description": "finish setup",
        "tags": [
        {  "tagName": "param",
               "values": ["event"]},
            {  "tagName": "playerversion",
               "values": ["Flash 10.2", "AIR 2.6"]},
            {  "tagName": "productversion",
               "values": ["Royale 0.9.7"]},
            {  "tagName": "langversion",
               "values": ["3.0"]}  ],
          "return": "void",
          "params": [{ "name": "event", "type": "org.apache.royale.events.Event"}]}
      ,
      { "type": "accessor",
        "access": "read-only",
        "return": "Array",
        "qname": "columnLists",
        "namespace": "public",
        "bindable": [],
        "details": [],
        "deprecated": {},
          "description": "An array of List objects the comprise the columns of the DataGrid.",
        "tags": [
          ]},
      { "type": "accessor",
        "access": "read-only",
        "return": "org.apache.royale.core.IUIBase",
        "qname": "listArea",
        "namespace": "public",
        "bindable": [],
        "details": [],
        "deprecated": {},
          "description": "The area used to hold the columns",
        "tags": [
          ]},
      { "type": "accessor",
        "access": "read-only",
        "return": "org.apache.royale.core.IDataGridHeader",
        "qname": "header",
        "namespace": "public",
        "bindable": [],
        "details": [],
        "deprecated": {},
          "description": "Returns the component used as the header for the DataGrid.",
        "tags": [
          ]},
      { "type": "method",
        "qname": "handleCollectionChanged",
        "namespace": "protected",
        "bindable": [],
        "details": [],
        "deprecated": {},
          "description": "Handles the itemAdded event by adding the item.",
        "tags": [
        {  "tagName": "playerversion",
               "values": ["Flash 10.2", "AIR 2.6"]},
            {  "tagName": "productversion",
               "values": ["Royale 0.9.7"]},
            {  "tagName": "royaleignorecoercion",
               "values": ["org.apache.royale.jewel.supportClasses.datagrid.IDataGridColumnList"]},
            {  "tagName": "langversion",
               "values": ["3.0"]}  ],
          "return": "void",
          "params": [{ "name": "event", "type": "org.apache.royale.events.CollectionEvent"}]}
      ,
      { "type": "method",
        "qname": "handleItemAddedAndRemoved",
        "namespace": "protected",
        "bindable": [],
        "details": [],
        "deprecated": {},
          "description": "Handles the itemAdded event by adding the item.",
        "tags": [
        {  "tagName": "playerversion",
               "values": ["Flash 10.2", "AIR 2.6"]},
            {  "tagName": "productversion",
               "values": ["Royale 0.9.7"]},
            {  "tagName": "royaleignorecoercion",
               "values": ["org.apache.royale.jewel.supportClasses.datagrid.IDataGridColumnList"]},
            {  "tagName": "langversion",
               "values": ["3.0"]}  ],
          "return": "void",
          "params": [{ "name": "event", "type": "org.apache.royale.events.CollectionEvent"}]}
      ,
      { "type": "method",
        "qname": "proxyDispatchChange",
        "namespace": "public",
        "bindable": [],
        "details": [],
        "deprecated": {},
          "description": "",
        "tags": [
          ],
          "return": "void",
          "params": []}
      ]
  ,
  "events": [
  ]
  }
