{ "type": "class",
  "qname": "org.apache.royale.html.supportClasses.UIItemRendererBase",
  "baseClassname": "org.apache.royale.core.UIBase"
  ,
    "description": "The UIItemRendererBase class is the base class for all itemRenderers. An itemRenderer is used to display a single datum within a collection of data. Components such as a List use itemRenderers to show their dataProviders.",
  "tags": [
  {  "tagName": "playerversion",
         "values": ["Flash 10.2", "AIR 2.6"]},
      {  "tagName": "productversion",
         "values": ["Royale 0.0"]},
      {  "tagName": "langversion",
         "values": ["3.0"]}  ],
  "members": [
  { "type": "method",
        "qname": "org.apache.royale.html.supportClasses.UIItemRendererBase",
        "namespace": "",
          "description": "constructor.",
        "tags": [
        {  "tagName": "playerversion",
               "values": ["Flash 10.2", "AIR 2.6"]},
            {  "tagName": "productversion",
               "values": ["Royale 0.0"]},
            {  "tagName": "langversion",
               "values": ["3.0"]}  ],
          "return": "",
          "params": []}
      ,
      { "type": "accessor",
        "access": "read-write",
        "return": "Object",
        "qname": "itemRendererParent",
        "namespace": "public",
          "description": "The parent container for the itemRenderer instance.",
        "tags": [
        {  "tagName": "playerversion",
               "values": ["Flash 10.2", "AIR 2.6"]},
            {  "tagName": "productversion",
               "values": ["Royale 0.0"]},
            {  "tagName": "langversion",
               "values": ["3.0"]}  ]},
      { "type": "field",
        "qname": "mxmlContent",
        "return": "Array",
        "namespace": "public",
          "description": "",
        "tags": [
        {  "tagName": "playerversion",
               "values": ["Flash 10.2", "AIR 2.6"]},
            {  "tagName": "copy",
               "values": ["org.apache.royale.core.ItemRendererClassFactory#mxmlContent"]},
            {  "tagName": "productversion",
               "values": ["Royale 0.0"]},
            {  "tagName": "langversion",
               "values": ["3.0"]}  ]},
      { "type": "accessor",
        "access": "read-only",
        "return": "Array",
        "qname": "MXMLDescriptor",
        "namespace": "public",
          "description": "",
        "tags": [
        {  "tagName": "private",
               "values": []}  ]},
      { "type": "field",
        "qname": "backgroundColor",
        "return": "uint",
        "namespace": "public"},
      { "type": "field",
        "qname": "highlightColor",
        "return": "uint",
        "namespace": "public"},
      { "type": "field",
        "qname": "selectedColor",
        "return": "uint",
        "namespace": "public"},
      { "type": "field",
        "qname": "downColor",
        "return": "uint",
        "namespace": "public"},
      { "type": "field",
        "qname": "useColor",
        "return": "uint",
        "namespace": "protected"},
      { "type": "accessor",
        "access": "read-write",
        "return": "Object",
        "qname": "data",
        "namespace": "public",
        "bindable": ["__NoChangeEvent__"],
          "description": "The data being represented by this itemRenderer. This can be something simple like a String or a Number or something very complex.",
        "tags": [
        {  "tagName": "playerversion",
               "values": ["Flash 10.2", "AIR 2.6"]},
            {  "tagName": "productversion",
               "values": ["Royale 0.0"]},
            {  "tagName": "langversion",
               "values": ["3.0"]}  ]},
      { "type": "accessor",
        "access": "read-write",
        "return": "Object",
        "qname": "listData",
        "namespace": "public",
        "bindable": ["__NoChangeEvent__"],
          "description": "Additional data about the list structure the itemRenderer may find useful.",
        "tags": [
        {  "tagName": "playerversion",
               "values": ["Flash 10.2", "AIR 2.6"]},
            {  "tagName": "productversion",
               "values": ["Royale 0.0"]},
            {  "tagName": "langversion",
               "values": ["3.0"]}  ]},
      { "type": "accessor",
        "access": "read-write",
        "return": "String",
        "qname": "labelField",
        "namespace": "public",
          "description": "The name of the field within the data to use as a label. Some itemRenderers use this field to identify the value they should show while other itemRenderers ignore this if they are showing complex information."},
      { "type": "accessor",
        "access": "read-write",
        "return": "int",
        "qname": "index",
        "namespace": "public",
          "description": "The position with the dataProvider being shown by the itemRenderer instance.",
        "tags": [
        {  "tagName": "playerversion",
               "values": ["Flash 10.2", "AIR 2.6"]},
            {  "tagName": "productversion",
               "values": ["Royale 0.0"]},
            {  "tagName": "langversion",
               "values": ["3.0"]}  ]},
      { "type": "accessor",
        "access": "read-write",
        "return": "Boolean",
        "qname": "hovered",
        "namespace": "public",
          "description": "Whether or not the itemRenderer is in a hovered state.",
        "tags": [
        {  "tagName": "playerversion",
               "values": ["Flash 10.2", "AIR 2.6"]},
            {  "tagName": "productversion",
               "values": ["Royale 0.0"]},
            {  "tagName": "langversion",
               "values": ["3.0"]}  ]},
      { "type": "accessor",
        "access": "read-write",
        "return": "Boolean",
        "qname": "selected",
        "namespace": "public",
          "description": "Whether or not the itemRenderer is in a selected state.",
        "tags": [
        {  "tagName": "playerversion",
               "values": ["Flash 10.2", "AIR 2.6"]},
            {  "tagName": "productversion",
               "values": ["Royale 0.0"]},
            {  "tagName": "langversion",
               "values": ["3.0"]}  ]},
      { "type": "accessor",
        "access": "read-write",
        "return": "Boolean",
        "qname": "down",
        "namespace": "public",
          "description": "Whether or not the itemRenderer is in a down (or pre-selected) state.",
        "tags": [
        {  "tagName": "playerversion",
               "values": ["Flash 10.2", "AIR 2.6"]},
            {  "tagName": "productversion",
               "values": ["Royale 0.0"]},
            {  "tagName": "langversion",
               "values": ["3.0"]}  ]},
      { "type": "method",
        "qname": "adjustSize",
        "namespace": "public",
          "description": "This function is called whenever the itemRenderer changes size. Sub-classes should override this method an handle the size change.",
        "tags": [
        {  "tagName": "playerversion",
               "values": ["Flash 10.2", "AIR 2.6"]},
            {  "tagName": "productversion",
               "values": ["Royale 0.0"]},
            {  "tagName": "langversion",
               "values": ["3.0"]}  ],
          "return": "void",
          "params": []}
      ]
  }
