{ "type": "class",
  "qname": "mx.charts.GridLines",
  "baseClassname": "mx.charts.chartClasses.ChartElement"
  ,
    "description": "The GridLines class draws grid lines inside the data area of the chart. Flex can draw lines horizontally, vertically, or both.  <p>Flex draws grid lines aligned to the tick marks of the parent chart. By default, Flex draws one line for every tick mark along the appropriate axis.</p>  <p>You typically use the GridLines class as a child tag of a chart control's <code>backgroundElements</code> property or <code>annotationElements</code> property.</p>   <p>The <code>&lt;mx:GridLines&gt;</code> tag inherits all the properties of its parent classes and adds the following properties:</p>  <pre> &lt;mx:GridLines <strong>Styles</strong> gridDirection=\\&quot;horizontal|vertical|both\\&quot; horizontalAlternateFill=\\&quot;null\\&quot; horizontalChangeCount=\\&quot;1\\&quot; horizontalFill=\\&quot;null\\&quot; horizontalOriginStroke=\\&quot;<i>IStroke; No default</i>\\&quot; horizontalShowOrigin=\\&quot;<i>Default depends on type of chart</i>\\&quot; horizontalStroke=\\&quot;<i>IStroke; No default</i>\\&quot; horizontalTickAligned=\\&quot;true|false\\&quot; verticalAlternateFill=\\&quot;null\\&quot; verticalChangeCount=\\&quot;1\\&quot; verticalFill=\\&quot;null\\&quot; verticalOriginStroke=\\&quot;<i>IStroke; No default</i>\\&quot; verticalShowOrigin=\\&quot;<i>Default depends on type of chart</i>\\&quot; verticalStroke=\\&quot;<i>IStroke; No default</i>\\&quot; verticalTickAligned=\\&quot;true|false\\&quot; /&gt; </pre>",
  "tags": [
  {  "tagName": "includeExample",
         "values": ["examples/GridLinesExample.mxml"]},
      {  "tagName": "mxml",
         "values": []},
      {  "tagName": "playerversion",
         "values": ["Flash 9", "AIR 1.1"]},
      {  "tagName": "productversion",
         "values": ["Flex 3"]},
      {  "tagName": "langversion",
         "values": ["3.0"]}  ],
  "members": [
  { "type": "method",
        "qname": "mx.charts.GridLines",
        "namespace": "",
        "bindable": [],
        "details": [],
        "deprecated": {},
          "description": "Constructor.",
        "tags": [
        {  "tagName": "playerversion",
               "values": ["Flash 9", "AIR 1.1"]},
            {  "tagName": "productversion",
               "values": ["Flex 3"]},
            {  "tagName": "langversion",
               "values": ["3.0"]}  ],
          "return": "",
          "params": []}
      ,
      { "type": "accessor",
        "access": "read-write",
        "return": "mx.core.IFlexModuleFactory",
        "qname": "moduleFactory",
        "namespace": "public",
        "bindable": [],
        "details": ["override"],
        "deprecated": {},
          "description": "",
        "tags": [
        {  "tagName": "inheritDoc",
               "values": []},
            {  "tagName": "playerversion",
               "values": ["Flash 9", "AIR 1.1"]},
            {  "tagName": "productversion",
               "values": ["Flex 3"]},
            {  "tagName": "langversion",
               "values": ["3.0"]}  ]},
      { "type": "method",
        "qname": "setActualSize",
        "namespace": "public",
        "bindable": [],
        "details": ["override"],
        "deprecated": {},
          "description": "",
        "tags": [
        {  "tagName": "inheritDoc",
               "values": []},
            {  "tagName": "playerversion",
               "values": ["Flash 9", "AIR 1.1"]},
            {  "tagName": "productversion",
               "values": ["Flex 3"]},
            {  "tagName": "langversion",
               "values": ["3.0"]}  ],
          "return": "void",
          "params": [{ "name": "w", "type": "Number"},
        { "name": "h", "type": "Number"}]}
      ]
  }
