{ "type": "class",
  "qname": "org.apache.royale.mdl.itemRenderers.MenuItemRenderer",
  "baseClassname": "org.apache.royale.html.supportClasses.MXMLItemRenderer"
  ,
    "description": "The MenuItemRenderer class creates a MDL menu item",
  "tags": [
  {  "tagName": "playerversion",
         "values": ["Flash 10.2", "AIR 2.6"]},
      {  "tagName": "productversion",
         "values": ["Royale 0.8"]},
      {  "tagName": "langversion",
         "values": ["3.0"]}  ],
  "members": [
  { "type": "method",
        "qname": "org.apache.royale.mdl.itemRenderers.MenuItemRenderer",
        "namespace": "",
        "bindable": [],
        "details": [],
        "deprecated": {},
          "description": "Constructor.",
        "tags": [
        {  "tagName": "playerversion",
               "values": ["Flash 10.2", "AIR 2.6"]},
            {  "tagName": "productversion",
               "values": ["Royale 0.8"]},
            {  "tagName": "langversion",
               "values": ["3.0"]}  ],
          "return": "",
          "params": []}
      ,
      { "type": "accessor",
        "access": "read-write",
        "return": "String",
        "qname": "text",
        "namespace": "public",
        "bindable": [],
        "details": [],
        "deprecated": {},
          "description": "The text of the menu item",
        "tags": [
        {  "tagName": "playerversion",
               "values": ["Flash 10.2", "AIR 2.6"]},
            {  "tagName": "productversion",
               "values": ["Royale 0.8"]},
            {  "tagName": "langversion",
               "values": ["3.0"]}  ]},
      { "type": "accessor",
        "access": "read-write",
        "return": "Object",
        "qname": "data",
        "namespace": "public",
        "bindable": [],
        "details": ["override"],
        "deprecated": {},
          "description": "Sets the data value and uses the String version of the data for display.",
        "tags": [
        {  "tagName": "param",
               "values": ["Object data The object being displayed by the itemRenderer instance."]},
            {  "tagName": "playerversion",
               "values": ["Flash 10.2", "AIR 2.6"]},
            {  "tagName": "productversion",
               "values": ["Royale 0.8"]},
            {  "tagName": "langversion",
               "values": ["3.0"]}  ]},
      { "type": "method",
        "qname": "createElement",
        "namespace": "protected",
        "bindable": [],
        "details": ["override"],
        "deprecated": {},
          "description": "",
        "tags": [
        {  "tagName": "royaleignorecoercion",
               "values": ["org.apache.royale.core.WrappedHTMLElement", "Text"]}  ],
          "return": "org.apache.royale.core.WrappedHTMLElement",
          "params": []}
      ,
      { "type": "accessor",
        "access": "read-write",
        "return": "Boolean",
        "qname": "divider",
        "namespace": "public",
        "bindable": [],
        "details": [],
        "deprecated": {},
          "description": "A boolean flag to activate &quot;mdl-menu__item--full-bleed-divider&quot; effect selector. Modifies an item to have a full bleed divider between it and the next list item.",
        "tags": [
        {  "tagName": "playerversion",
               "values": ["Flash 10.2", "AIR 2.6"]},
            {  "tagName": "productversion",
               "values": ["Royale 0.8"]},
            {  "tagName": "langversion",
               "values": ["3.0"]}  ]},
      { "type": "field",
        "qname": "_ripple",
        "return": "Boolean",
        "namespace": "protected",
        "bindable": [],
        "details": [],
        "deprecated": {}},
      { "type": "accessor",
        "access": "read-write",
        "return": "Boolean",
        "qname": "ripple",
        "namespace": "public",
        "bindable": [],
        "details": [],
        "deprecated": {},
          "description": "A boolean flag to activate &quot;mdl-js-ripple-effect&quot; effect selector.",
        "tags": [
        {  "tagName": "playerversion",
               "values": ["Flash 10.2", "AIR 2.6"]},
            {  "tagName": "productversion",
               "values": ["Royale 0.8"]},
            {  "tagName": "langversion",
               "values": ["3.0"]}  ]}]
  }
