{ "type": "class",
  "qname": "org.apache.royale.jewel.beads.controls.tristatecheckbox.TriStateCheckBoxLabelState",
  "baseClassname": "org.apache.royale.core.Bead"
  ,
    "description": "The TriStateCheckBoxLabelState bead allows us to display a different Text for each state.",
  "tags": [
    ],
  "members": [
  { "type": "method",
        "qname": "org.apache.royale.jewel.beads.controls.tristatecheckbox.TriStateCheckBoxLabelState",
        "namespace": "",
        "bindable": [],
        "details": [],
        "deprecated": {},
          "description": "",
        "tags": [
          ],
          "return": "",
          "params": []}
      ,
      { "type": "accessor",
        "access": "write-only",
        "return": "org.apache.royale.core.IStrand",
        "qname": "strand",
        "namespace": "public",
        "bindable": [],
        "details": ["override"],
        "deprecated": {},
          "description": "",
        "tags": [
        {  "tagName": "playerversion",
               "values": ["Flash 10.2", "AIR 2.6"]},
            {  "tagName": "copy",
               "values": ["org.apache.royale.core.IBead#strand"]},
            {  "tagName": "productversion",
               "values": ["Royale 0.9.6"]},
            {  "tagName": "royaleignorecoercion",
               "values": ["org.apache.royale.events.IEventDispatcher;"]},
            {  "tagName": "langversion",
               "values": ["3.0"]}  ]},
      { "type": "method",
        "qname": "textLabelChangeHandler",
        "namespace": "protected",
        "bindable": [],
        "details": [],
        "deprecated": {},
          "description": "",
        "tags": [
          ],
          "return": "void",
          "params": [{ "name": "event", "type": "org.apache.royale.events.Event"}]}
      ,
      { "type": "method",
        "qname": "updateHost",
        "namespace": "protected",
        "bindable": [],
        "details": [],
        "deprecated": {},
          "description": "",
        "tags": [
          ],
          "return": "void",
          "params": []}
      ,
      { "type": "accessor",
        "access": "read-write",
        "return": "String",
        "qname": "indeterminateText",
        "namespace": "public",
        "bindable": [],
        "details": [],
        "deprecated": {},
          "description": "",
        "tags": [
          ]},
      { "type": "accessor",
        "access": "read-write",
        "return": "String",
        "qname": "uncheckedText",
        "namespace": "public",
        "bindable": [],
        "details": [],
        "deprecated": {},
          "description": "",
        "tags": [
          ]},
      { "type": "accessor",
        "access": "read-write",
        "return": "String",
        "qname": "checkedText",
        "namespace": "public",
        "bindable": [],
        "details": [],
        "deprecated": {},
          "description": "",
        "tags": [
          ]}]
  ,
  "events": [
  ]
  }
